meiosis/__init__.py
meiosis/api/__init__.py
meiosis/api/export.py
meiosis/Domain/__init__.py
meiosis/Domain/entity.py
meiosis/Domain/entity_info.py
meiosis/Domain/image_frame.py
meiosis/Domain/map_names.py
meiosis/services/__init__.py
meiosis/services/image_exporter.py
meiosis/services/image_handler.py
meiosis/services/image_storage.py
meiosis/services/mapping/__init__.py
meiosis/services/mapping/standard_map.py
meiosis/services/meiosis_factory.py
meiosis/services/transformers/__init__.py
meiosis/services/transformers/copy_component.py
meiosis/services/transformers/image_transformer.py
meiosis/services/transformers/mapping_component.py
meiosis/services/transformers/rotator_component.py
meiosis/services/transformers/transformer.py
meiosis/services/transformers/transformer_builder.py
meiosis-0.1.5.dist-info/licenses/LICENSE
meiosis-0.1.5.dist-info/METADATA
meiosis-0.1.5.dist-info/WHEEL
meiosis-0.1.5.dist-info/RECORD
