Metadata-Version: 2.4
Name: meiosis
Version: 0.1.5
Summary: Meiosis is a Python package for creating new Images, usable for generating extra image data for ML-workflows. Thank you for using the Meiosis package.
License: MIT
License-File: LICENSE
Author: desalami@proton.me
Requires-Python: >= 3.12
Classifier: License :: OSI Approved :: MIT License
Classifier: Programming Language :: Python :: 3
Classifier: Programming Language :: Python :: 3.12
Classifier: Programming Language :: Python :: 3.13
Classifier: Programming Language :: Python :: 3.14
Requires-Dist: coverage (>=7.13.0,<8.0.0)
Requires-Dist: numpy (>=2.3.5,<3.0.0)
Requires-Dist: pillow (>=12.0.0,<13.0.0)
Requires-Dist: pytest (>=9.0.1,<10.0.0)
Project-URL: Homepage, https://github.com/Portfolio-Xin-Wang/ImageCopier
Project-URL: Issues, https://github.com/Portfolio-Xin-Wang/ImageCopier/issues
